Metadata-Version: 1.1
Name: django-mp-avtopro
Version: 0.1
Summary: Django avtopro apps
Home-page: https://github.com/pmaigutyak/mp-avtopro
Author: Paul Maigutyak
Author-email: pmaigutyak@gmail.com
License: MIT
Download-URL: https://github.com/pmaigutyak/mp-avtopro/archive/0.1.tar.gz
Platform: UNKNOWN
